odoo10_addon_account_move_line_payable_receivable_filter-10.0.1.0.0-py2.7-nspkg.pth
odoo10_addon_account_move_line_payable_receivable_filter-10.0.1.0.0.dist-info/top_level.txt
odoo10_addon_account_move_line_payable_receivable_filter-10.0.1.0.0.dist-info/WHEEL
odoo10_addon_account_move_line_payable_receivable_filter-10.0.1.0.0.dist-info/RECORD
odoo10_addon_account_move_line_payable_receivable_filter-10.0.1.0.0.dist-info/metadata.json
odoo10_addon_account_move_line_payable_receivable_filter-10.0.1.0.0.dist-info/DESCRIPTION.rst
odoo10_addon_account_move_line_payable_receivable_filter-10.0.1.0.0.dist-info/METADATA
odoo10_addon_account_move_line_payable_receivable_filter-10.0.1.0.0.dist-info/namespace_packages.txt
odoo/addons/account_move_line_payable_receivable_filter/__manifest__.py
odoo/addons/account_move_line_payable_receivable_filter/__init__.py
odoo/addons/account_move_line_payable_receivable_filter/README.rst
odoo/addons/account_move_line_payable_receivable_filter/i18n/es.po
odoo/addons/account_move_line_payable_receivable_filter/i18n/sl.po
odoo/addons/account_move_line_payable_receivable_filter/i18n/de.po
odoo/addons/account_move_line_payable_receivable_filter/i18n/fr.po
odoo/addons/account_move_line_payable_receivable_filter/i18n/fr_BE.po
odoo/addons/account_move_line_payable_receivable_filter/views/account_move_line_view.xml
odoo/addons/account_move_line_payable_receivable_filter/static/description/icon.png
